bench/shor_main.py
bench/QuantumFactoring.py
bench/qcbm_main.py
qdd/__init__.py
qdd/qdd_job.py
qdd/qdd_backend.py
qdd/qdd_gate.py
qdd/pyQDD.cpython-311-x86_64-linux-gnu.so
qdd/qdd_sv_backend.py
qdd/qdd_failed_job.py
qdd/qdd_provider.py
qdd/circuit_property.py
qdd/qdd_sampler.py
qdd/qdd_estimator.py
qdd/qdd_utils.py
qdd-0.2.7.dist-info/RECORD
qdd-0.2.7.dist-info/WHEEL
qdd-0.2.7.dist-info/METADATA
qdd-0.2.7.dist-info/top_level.txt
qdd-0.2.7.dist-info/licenses/LICENSE.txt
