Metadata-Version: 2.4
Name: qdd
Version: 0.2.7
Summary: Qiskit Provider for QDD
Author-email: Yusuke Kimura <yusuke-kimura@fujitsu.com>
License: Copyright (c) 2022-2023 Fujitsu Limited and Li Shaowen
Classifier: Programming Language :: Python :: 3
Classifier: Programming Language :: Python :: 3.9
Classifier: Programming Language :: Python :: 3.10
Classifier: Programming Language :: Python :: 3.11
Classifier: Programming Language :: Python :: 3.12
Requires-Python: <3.13,>=3.9
License-File: LICENSE.txt
Requires-Dist: qiskit~=2.2.0
Provides-Extra: test
Requires-Dist: pytest>=7.2.2; extra == "test"
Requires-Dist: pybind11>=2.10.4; extra == "test"
Requires-Dist: qiskit-aer>=0.13.3; extra == "test"
Dynamic: license-file
